{
	"id": "eRYzCWSZ4bsv4LH",
	"json": "{\"id\":\"eRYzCWSZ4bsv4LH\",\"url\":\"https://seoprimehub.com/\",\"loadedUrl\":\"https://seoprimehub.com/\",\"uniqueKey\":\"https://seoprimehub.com/:8fdde5f9-6996-4845-b914-43c3466eb630\",\"method\":\"GET\",\"noRetry\":false,\"retryCount\":0,\"errorMessages\":[],\"headers\":{},\"userData\":{\"label\":\"on-page\",\"__crawlee\":{\"state\":4}},\"handledAt\":\"2025-03-22T06:30:55.642Z\"}",
	"method": "GET",
	"orderNo": null,
	"retryCount": 0,
	"uniqueKey": "https://seoprimehub.com/:8fdde5f9-6996-4845-b914-43c3466eb630",
	"url": "https://seoprimehub.com/"
}